inngest/__init__.py
inngest/digital_ocean.py
inngest/django.py
inngest/fast_api.py
inngest/flask.py
inngest/py.typed
inngest/tornado.py
inngest/_internal/__init__.py
inngest/_internal/async_lib.py
inngest/_internal/config_lib.py
inngest/_internal/const.py
inngest/_internal/const_test.py
inngest/_internal/env_lib.py
inngest/_internal/errors.py
inngest/_internal/function.py
inngest/_internal/function_test.py
inngest/_internal/log.py
inngest/_internal/net.py
inngest/_internal/net_test.py
inngest/_internal/serializer_lib.py
inngest/_internal/transforms.py
inngest/_internal/transforms_test.py
inngest/_internal/types.py
inngest/_internal/types_test.py
inngest/_internal/client_lib/__init__.py
inngest/_internal/client_lib/client.py
inngest/_internal/client_lib/client_test.py
inngest/_internal/client_lib/models.py
inngest/_internal/client_lib/utils.py
inngest/_internal/comm_lib/README.md
inngest/_internal/comm_lib/__init__.py
inngest/_internal/comm_lib/handler.py
inngest/_internal/comm_lib/handler_test.py
inngest/_internal/comm_lib/models.py
inngest/_internal/comm_lib/utils.py
inngest/_internal/execution_lib/__init__.py
inngest/_internal/execution_lib/base.py
inngest/_internal/execution_lib/models.py
inngest/_internal/execution_lib/utils.py
inngest/_internal/execution_lib/v0.py
inngest/_internal/middleware_lib/__init__.py
inngest/_internal/middleware_lib/log.py
inngest/_internal/middleware_lib/manager.py
inngest/_internal/middleware_lib/middleware.py
inngest/_internal/server_lib/README.md
inngest/_internal/server_lib/__init__.py
inngest/_internal/server_lib/consts.py
inngest/_internal/server_lib/event.py
inngest/_internal/server_lib/event_test.py
inngest/_internal/server_lib/execution_request.py
inngest/_internal/server_lib/inspection.py
inngest/_internal/server_lib/registration.py
inngest/_internal/server_lib/registration_test.py
inngest/_internal/step_lib/__init__.py
inngest/_internal/step_lib/base.py
inngest/_internal/step_lib/group.py
inngest-0.5.12.dist-info/METADATA
inngest-0.5.12.dist-info/WHEEL
inngest-0.5.12.dist-info/RECORD
